stitch_core-0.1.29.dist-info/METADATA
stitch_core-0.1.29.dist-info/WHEEL
stitch_core/__init__.py
stitch_core/py.typed
stitch_core/stitch_core.cpython-311-darwin.so
stitch_core-0.1.29.dist-info/RECORD
